LICENSE
MANIFEST.in
README.md
djangoSCA.py
djangoSCA.rules
setup.py
DjangoSCA.egg-info/PKG-INFO
DjangoSCA.egg-info/SOURCES.txt
DjangoSCA.egg-info/dependency_links.txt
DjangoSCA.egg-info/top_level.txt
djangoSCAclasses/ContentReader.py
djangoSCAclasses/MyParser.py
djangoSCAclasses/SettingsCheck.py
djangoSCAclasses/__init__.py