Metadata-Version: 1.0
Name: DjangoSCA
Version: 1.3i
Summary: Django Static Source Code Analyzer
Home-page: https://bitbucket.org/jsthyer/djangosca
Author: Joff Thyer
Author-email: jsthyer@gmail.com
License: GPLv3
Platform: UNKNOWN
